lunaai/__init__.py
lunaai/chatbot.py
lunaai/urls.py
lunaai-0.3.0.dist-info/METADATA
lunaai-0.3.0.dist-info/WHEEL
lunaai-0.3.0.dist-info/entry_points.txt
lunaai-0.3.0.dist-info/top_level.txt
lunaai-0.3.0.dist-info/RECORD
