Metadata-Version: 2.1
Name: lunaai
Version: 0.3.0
Summary: A retrieval-based QnA and code generation chatbot using sentence-transformer embeddings.
Author: Joydeep Dutta
Author-email: joydeep.development.cse@gmail.com
Classifier: Programming Language :: Python :: 3
Classifier: License :: OSI Approved :: MIT License
Classifier: Operating System :: OS Independent
Requires-Python: >=3.7
Requires-Dist: gdown
Requires-Dist: numpy
Requires-Dist: pandas
Requires-Dist: sentence-transformers
Requires-Dist: scikit-learn
Requires-Dist: nltk
Requires-Dist: rapidfuzz
